django_nginx_generator/__init__.py
django_nginx_generator/cli.py
django_nginx_generator-1.1.0.dist-info/licenses/LICENSE
django_nginx_generator-1.1.0.dist-info/METADATA
django_nginx_generator-1.1.0.dist-info/WHEEL
django_nginx_generator-1.1.0.dist-info/entry_points.txt
django_nginx_generator-1.1.0.dist-info/top_level.txt
django_nginx_generator-1.1.0.dist-info/RECORD
