Metadata-Version: 2.4
Name: django-nginx-generator
Version: 1.1.0
Summary: CLI tool to auto-generate production-grade Nginx configs for Django
Home-page: https://github.com/amirreza-jabbari/django-nginx-generator
Author: Amirreza Jabbari
Author-email: amirrezajabbari79@gmail.com
Classifier: Development Status :: 5 - Production/Stable
Classifier: Environment :: Console
Classifier: Framework :: Django
Classifier: Intended Audience :: Developers
Classifier: License :: OSI Approved :: MIT License
Classifier: Programming Language :: Python :: 3
Classifier: Topic :: System :: Systems Administration
License-File: LICENSE
Requires-Dist: click>=8.0
Requires-Dist: jinja2>=3.0
Requires-Dist: Django>=3.2
Dynamic: author
Dynamic: author-email
Dynamic: classifier
Dynamic: description
Dynamic: description-content-type
Dynamic: home-page
Dynamic: license-file
Dynamic: requires-dist
Dynamic: summary
